MongodbJiaochengCYuyanBianchengWang/README.md
MongodbJiaochengCYuyanBianchengWang/__init__.py
MongodbJiaochengCYuyanBianchengWang/__main__.py
MongodbJiaochengCYuyanBianchengWang/file.epub
MongodbJiaochengCYuyanBianchengWang/index.html
MongodbJiaochengCYuyanBianchengWang/css/__init__.py
MongodbJiaochengCYuyanBianchengWang/css/annotations.css
MongodbJiaochengCYuyanBianchengWang/css/main.css
MongodbJiaochengCYuyanBianchengWang/css/normalize.css
MongodbJiaochengCYuyanBianchengWang/css/popup.css
MongodbJiaochengCYuyanBianchengWang/font/__init__.py
MongodbJiaochengCYuyanBianchengWang/font/fontello.eot
MongodbJiaochengCYuyanBianchengWang/font/fontello.svg
MongodbJiaochengCYuyanBianchengWang/font/fontello.ttf
MongodbJiaochengCYuyanBianchengWang/font/fontello.woff
MongodbJiaochengCYuyanBianchengWang/img/__init__.py
MongodbJiaochengCYuyanBianchengWang/img/annotator-glyph-sprite.png
MongodbJiaochengCYuyanBianchengWang/img/annotator-icon-sprite.png
MongodbJiaochengCYuyanBianchengWang/img/apple-touch-icon.png
MongodbJiaochengCYuyanBianchengWang/img/cancelfullscreen.png
MongodbJiaochengCYuyanBianchengWang/img/close.png
MongodbJiaochengCYuyanBianchengWang/img/fullscreen.png
MongodbJiaochengCYuyanBianchengWang/img/loader.gif
MongodbJiaochengCYuyanBianchengWang/img/menu-icon.png
MongodbJiaochengCYuyanBianchengWang/img/save.png
MongodbJiaochengCYuyanBianchengWang/img/saved.png
MongodbJiaochengCYuyanBianchengWang/img/settings-s.png
MongodbJiaochengCYuyanBianchengWang/img/settings.png
MongodbJiaochengCYuyanBianchengWang/img/star.png
MongodbJiaochengCYuyanBianchengWang/js/__init__.py
MongodbJiaochengCYuyanBianchengWang/js/epub.js
MongodbJiaochengCYuyanBianchengWang/js/epub.min.js
MongodbJiaochengCYuyanBianchengWang/js/epub.min.map
MongodbJiaochengCYuyanBianchengWang/js/hooks.min.js
MongodbJiaochengCYuyanBianchengWang/js/hooks.min.map
MongodbJiaochengCYuyanBianchengWang/js/reader.js
MongodbJiaochengCYuyanBianchengWang/js/reader.js.map
MongodbJiaochengCYuyanBianchengWang/js/reader.min.js
mongodb_jiaocheng_c_yuyan_biancheng_wang-2024.3.5.0.dist-info/METADATA
mongodb_jiaocheng_c_yuyan_biancheng_wang-2024.3.5.0.dist-info/WHEEL
mongodb_jiaocheng_c_yuyan_biancheng_wang-2024.3.5.0.dist-info/entry_points.txt
mongodb_jiaocheng_c_yuyan_biancheng_wang-2024.3.5.0.dist-info/top_level.txt
mongodb_jiaocheng_c_yuyan_biancheng_wang-2024.3.5.0.dist-info/RECORD
